funcy/__init__.py
funcy/_inspect.py
funcy/calc.py
funcy/colls.py
funcy/compat.py
funcy/debug.py
funcy/decorators.py
funcy/flow.py
funcy/funcmakers.py
funcy/funcolls.py
funcy/funcs.py
funcy/objects.py
funcy/primitives.py
funcy/py2.py
funcy/py3.py
funcy/seqs.py
funcy/strings.py
funcy/tree.py
funcy/types.py
funcy-1.13.dist-info/LICENSE
funcy-1.13.dist-info/METADATA
funcy-1.13.dist-info/WHEEL
funcy-1.13.dist-info/top_level.txt
funcy-1.13.dist-info/RECORD
